hopla/__init__.py
hopla/executor.py
hopla/info.py
hopla/pbs.py
hopla/utils.py
hopla-2.0.0.dist-info/METADATA
hopla-2.0.0.dist-info/WHEEL
hopla-2.0.0.dist-info/top_level.txt
hopla-2.0.0.dist-info/RECORD
