Metadata-Version: 2.1
Name: hopla
Version: 2.0.0
Author-email: hopla developers <antoine.grigis@cea.fr>
License: CeCILL-B
Project-URL: Source, https://github.com/AGrigis/hopla
Project-URL: Tracker, https://github.com/AGrigis/hopla/issues
Platform: Linux
Platform: OSX
Classifier: Development Status :: 1 - Planning
Classifier: Environment :: Console
Classifier: Operating System :: OS Independent
Classifier: Programming Language :: Python
Classifier: Topic :: Scientific/Engineering
Requires-Python: >=3.8
Requires-Dist: tqdm
